{
  "content": [
    {
      "type": "text",
      "text": "Found 53 contacts (page 1):"
    },
    {
      "type": "text",
      "text": "Contact: Basket Shop\nID: 305ca5cf-497d-4fee-a161-cdb30e6be989\nFirst Name: Mary\nLast Name: Munn\nEmail: shop@basketshop.co\nType: Unknown\nLast Updated: Sat Jul 04 2026 15:18:19 GMT+0100 (英国夏令时间)\nStatus: ACTIVE"
    },
    {
      "type": "text",
      "text": "Contact: Abby & Wells\nID: 98073808-f678-4429-b4c2-ab73dab5b2ea\nNo email\nType: Unknown\nLast Updated: Sat Jul 04 2026 18:38:25 GMT+0100 (英国夏令时间)\nStatus: ACTIVE"
    },
    {
      "type": "text",
      "text": "Contact: Luna Cafe\nID: 20cdb5a7-81b1-488f-aae4-d82e1691e13a\nNo email\nType: Unknown\nLast Updated: Sat Jul 04 2026 18:38:25 GMT+0100 (英国夏令时间)\nStatus: ACTIVE"
    },
    {
      "type": "text",
      "text": "Contact: Eastside Club\nID: f5a72079-e8ef-4d57-b36f-590206b9888e\nNo email\nType: Unknown\nLast Updated: Sat Jul 04 2026 18:38:25 GMT+0100 (英国夏令时间)\nStatus: ACTIVE"
    },
    {
      "type": "text",
      "text": "Contact: RITE Agency\nID: b800bd26-e034-4694-a81a-3e4d81184513\nNo email\nType: Unknown\nLast Updated: Sat Jul 04 2026 18:38:25 GMT+0100 (英国夏令时间)\nStatus: ACTIVE"
    },
    {
      "type": "text",
      "text": "Contact: arya cao\nID: 3e55a52d-e3a2-4d7c-bff1-f52723266ba2\nFirst Name: arya\nLast Name: cao\nEmail: seulgicao@gmail.com\nType: Unknown\nLast Updated: Sat Jul 04 2026 18:38:32 GMT+0100 (英国夏令时间)\nStatus: ACTIVE"
    },
    {
      "type": "text",
      "text": "Contact: arya cao\nID: 55d2f5fe-6820-4b69-8e80-710330642e9e\nFirst Name: arya\nLast Name: cao\nEmail: seulgicao@gmail.com\nType: Unknown\nLast Updated: Sat Jul 04 2026 18:38:32 GMT+0100 (英国夏令时间)\nStatus: ACTIVE"
    },
    {
      "type": "text",
      "text": "Contact: Gable Print\nID: adf801de-a142-4670-906f-0d46c5d7c693\nNo email\nType: Unknown\nLast Updated: Sat Jul 04 2026 19:03:42 GMT+0100 (英国夏令时间)\nStatus: ACTIVE"
    },
    {
      "type": "text",
      "text": "Contact: Office Supplies Company\nID: 74ea95ea-6e1e-435d-9c30-0dff8ae1bd80\nNo email\nType: Unknown\nLast Updated: Sat Jul 04 2026 19:03:42 GMT+0100 (英国夏令时间)\nStatus: ACTIVE"
    },
    {
      "type": "text",
      "text": "Contact: Wilson Periodicals\nID: bc446de5-971e-48b5-8efd-1745149844ef\nNo email\nType: Unknown\nDefault Currency: GBP\nLast Updated: Sat Jul 04 2026 19:03:42 GMT+0100 (英国夏令时间)\nStatus: ACTIVE"
    },
    {
      "type": "text",
      "text": "Contact: Fulton Airport Parking\nID: 289373e2-745c-4743-8b58-3008351f83dd\nNo email\nType: Unknown\nLast Updated: Sat Jul 04 2026 19:03:42 GMT+0100 (英国夏令时间)\nStatus: ACTIVE"
    },
    {
      "type": "text",
      "text": "Contact: Pret A Manger\nID: 2cac4876-91fb-4cb7-b969-340aa548f64a\nNo email\nType: Unknown\nDefault Currency: GBP\nLast Updated: Sat Jul 04 2026 19:03:42 GMT+0100 (英国夏令时间)\nStatus: ACTIVE"
    },
    {
      "type": "text",
      "text": "Contact: Brunswick Petals\nID: 5a83dcee-ee21-4ee8-b53b-381b93346256\nNo email\nType: Unknown\nLast Updated: Sat Jul 04 2026 19:03:42 GMT+0100 (英国夏令时间)\nStatus: ACTIVE"
    },
    {
      "type": "text",
      "text": "Contact: Ridgeway Bank\nID: 737982b0-2811-44c9-bdb3-3b26a3a6ef8c\nNo email\nType: Unknown\nLast Updated: Sat Jul 04 2026 19:03:42 GMT+0100 (英国夏令时间)\nStatus: ACTIVE"
    },
    {
      "type": "text",
      "text": "Contact: Coco Cafe\nID: f1c18eb1-cdc5-4f11-9867-666cbbc397fe\nNo email\nType: Unknown\nLast Updated: Sat Jul 04 2026 19:03:42 GMT+0100 (英国夏令时间)\nStatus: ACTIVE"
    },
    {
      "type": "text",
      "text": "Contact: 24 Locks\nID: e4c9d0e2-c285-4e85-b579-6d28b180c730\nNo email\nType: Unknown\nLast Updated: Sat Jul 04 2026 19:03:42 GMT+0100 (英国夏令时间)\nStatus: ACTIVE"
    },
    {
      "type": "text",
      "text": "Contact: Berry Brew\nID: b9d4332a-26a3-4577-8db2-6e830d4b07cd\nNo email\nType: Unknown\nLast Updated: Sat Jul 04 2026 19:03:42 GMT+0100 (英国夏令时间)\nStatus: ACTIVE"
    },
    {
      "type": "text",
      "text": "Contact: Melrose Parking\nID: 0b787601-82f5-438f-9fb7-7eeb0a09b2a0\nNo email\nType: Unknown\nLast Updated: Sat Jul 04 2026 19:03:42 GMT+0100 (英国夏令时间)\nStatus: ACTIVE"
    },
    {
      "type": "text",
      "text": "Contact: Espresso 31\nID: c82900a5-064c-46e1-9d8b-86404c6bfd01\nNo email\nType: Unknown\nLast Updated: Sat Jul 04 2026 19:03:42 GMT+0100 (英国夏令时间)\nStatus: ACTIVE"
    },
    {
      "type": "text",
      "text": "Contact: 7-Eleven\nID: bab779bc-c5fb-42cb-a888-953e8309711c\nNo email\nType: Unknown\nLast Updated: Sat Jul 04 2026 19:03:42 GMT+0100 (英国夏令时间)\nStatus: ACTIVE"
    },
    {
      "type": "text",
      "text": "Contact: Dimples Warehouse\nID: 4b0dd2ab-7cce-4a8a-8bdb-d49c3e2faf97\nNo email\nType: Unknown\nDefault Currency: GBP\nLast Updated: Sat Jul 04 2026 19:03:42 GMT+0100 (英国夏令时间)\nStatus: ACTIVE"
    },
    {
      "type": "text",
      "text": "Contact: Woolworths Market\nID: be45660b-46fe-412b-9c2e-f667fc5007c3\nNo email\nType: Unknown\nLast Updated: Sat Jul 04 2026 19:03:42 GMT+0100 (英国夏令时间)\nStatus: ACTIVE"
    },
    {
      "type": "text",
      "text": "Contact: Carlton Functions\nID: 4acf731f-af81-4ed3-96b2-0c408b2d98c0\nNo email\nType: Unknown\nLast Updated: Sat Jul 04 2026 19:03:42 GMT+0100 (英国夏令时间)\nStatus: ACTIVE"
    },
    {
      "type": "text",
      "text": "Contact: SMART Agency\nID: f5a77e82-50e3-4340-a6e0-13d6a482a08a\nNo email\nType: Unknown\nLast Updated: Sat Jul 04 2026 19:03:42 GMT+0100 (英国夏令时间)\nStatus: ACTIVE"
    },
    {
      "type": "text",
      "text": "Contact: Truxton Property Management\nID: aca6e01a-1815-474c-bd0f-18adfd95cfcb\nNo email\nType: Unknown\nLast Updated: Sat Jul 04 2026 19:03:42 GMT+0100 (英国夏令时间)\nStatus: ACTIVE"
    },
    {
      "type": "text",
      "text": "Contact: PC Complete\nID: cf8fa320-a527-496c-823e-22dd069d29e6\nNo email\nType: Unknown\nLast Updated: Sat Jul 04 2026 19:03:42 GMT+0100 (英国夏令时间)\nStatus: ACTIVE"
    },
    {
      "type": "text",
      "text": "Contact: Swanston Security\nID: 3a0d40a2-2698-4cf5-b7b2-30133c632ab6\nNo email\nType: Unknown\nLast Updated: Sat Jul 04 2026 19:03:42 GMT+0100 (英国夏令时间)\nStatus: ACTIVE"
    },
    {
      "type": "text",
      "text": "Contact: MCO Cleaning Services\nID: 8a593982-291c-4ec3-9a42-3dbccbc6e3c8\nNo email\nType: Unknown\nLast Updated: Sat Jul 04 2026 19:03:42 GMT+0100 (英国夏令时间)\nStatus: ACTIVE"
    },
    {
      "type": "text",
      "text": "Contact: ABC Furniture\nID: 699f0091-b127-4796-9f15-41a2f42abeb2\nFirst Name: Trish\nLast Name: Rawlings\nEmail: info@abfl.com\nType: Unknown\nDefault Currency: GBP\nLast Updated: Sat Jul 04 2026 19:03:42 GMT+0100 (英国夏令时间)\nStatus: ACTIVE"
    },
    {
      "type": "text",
      "text": "Contact: Gateway Motors\nID: f559658a-68da-42b1-81ae-42a96b6c6953\nNo email\nType: Unknown\nLast Updated: Sat Jul 04 2026 19:03:42 GMT+0100 (英国夏令时间)\nStatus: ACTIVE"
    },
    {
      "type": "text",
      "text": "Contact: Hoyt Productions\nID: 8894cc85-85c2-4fd2-9eb6-537179d1a12d\nNo email\nType: Unknown\nLast Updated: Sat Jul 04 2026 19:03:42 GMT+0100 (英国夏令时间)\nStatus: ACTIVE"
    },
    {
      "type": "text",
      "text": "Contact: PowerDirect\nID: dec56ceb-65e9-43b3-ac98-7fe09eb37e31\nNo email\nAP Tax Type: RRINPUT\nType: Unknown\nLast Updated: Sat Jul 04 2026 19:03:42 GMT+0100 (英国夏令时间)\nStatus: ACTIVE"
    },
    {
      "type": "text",
      "text": "Contact: Central Copiers\nID: 3828f379-afa5-4b2a-9000-9c53d75ba1c6\nNo email\nType: Unknown\nLast Updated: Sat Jul 04 2026 19:03:42 GMT+0100 (英国夏令时间)\nStatus: ACTIVE"
    },
    {
      "type": "text",
      "text": "Contact: Xero\nID: ac48c67d-3eea-44eb-96b1-9f7a89d9b761\nNo email\nType: Unknown\nLast Updated: Sat Jul 04 2026 19:03:42 GMT+0100 (英国夏令时间)\nStatus: ACTIVE"
    },
    {
      "type": "text",
      "text": "Contact: HMRC\nID: 1c842b26-90b8-4791-b2d5-a9aea8078aa5\nNo email\nType: Unknown\nLast Updated: Sat Jul 04 2026 19:03:42 GMT+0100 (英国夏令时间)\nStatus: ACTIVE"
    },
    {
      "type": "text",
      "text": "Contact: Bayside Wholesale\nID: 2dc0ef7c-582f-4542-963b-dbdc069e4819\nNo email\nType: Unknown\nLast Updated: Sat Jul 04 2026 19:03:42 GMT+0100 (英国夏令时间)\nStatus: ACTIVE"
    },
    {
      "type": "text",
      "text": "Contact: Net Connect\nID: 97cc88ca-f89b-41f0-b8b9-e750b6f2f1d9\nNo email\nAP Tax Type: INPUT2\nType: Unknown\nLast Updated: Sat Jul 04 2026 19:03:42 GMT+0100 (英国夏令时间)\nStatus: ACTIVE"
    },
    {
      "type": "text",
      "text": "Contact: Capital Cab Co\nID: 51cbbfb0-8dc9-41aa-aad6-eb93b3cc40c6\nNo email\nType: Unknown\nLast Updated: Sat Jul 04 2026 19:03:42 GMT+0100 (英国夏令时间)\nStatus: ACTIVE"
    },
    {
      "type": "text",
      "text": "Contact: Hamilton Smith Ltd\nID: af0091a9-82ef-4cac-9fd6-22c095ac6a58\nEmail: info@hsg.co\nType: Unknown\nLast Updated: Sat Jul 04 2026 19:03:42 GMT+0100 (英国夏令时间)\nStatus: ACTIVE"
    },
    {
      "type": "text",
      "text": "Contact: Bayside Club\nID: 362819c9-f285-4d09-ac95-26327863adac\nFirst Name: Bob\nLast Name: Partridge\nEmail: bob.partridge@bayclub.co\nAR Tax Type: OUTPUT2\nAP Tax Type: INPUT2\nType: Unknown\nLast Updated: Sat Jul 04 2026 19:03:42 GMT+0100 (英国夏令时间)\nStatus: ACTIVE"
    },
    {
      "type": "text",
      "text": "Contact: City Limousines\nID: c523e12f-8b74-4d3a-bbd8-32d7a2f598b4\nFirst Name: Martin\nLast Name: Dale\nEmail: martyd@citylim.co\nType: Unknown\nLast Updated: Sat Jul 04 2026 19:03:42 GMT+0100 (英国夏令时间)\nStatus: ACTIVE"
    },
    {
      "type": "text",
      "text": "Contact: Bank West\nID: a852a44c-3d8f-4c4b-a628-3a2c2121b9b1\nNo email\nType: Unknown\nLast Updated: Sat Jul 04 2026 19:03:42 GMT+0100 (英国夏令时间)\nStatus: ACTIVE"
    },
    {
      "type": "text",
      "text": "Contact: Petrie McLoud Watson & Associates\nID: 7eccc5ab-cee8-4af4-b2a9-3f9b17f03095\nFirst Name: Morris\nLast Name: McKenzie\nEmail: mm@pmwla.co\nType: Unknown\nLast Updated: Sat Jul 04 2026 19:03:42 GMT+0100 (英国夏令时间)\nStatus: ACTIVE"
    },
    {
      "type": "text",
      "text": "Contact: DIISR - Small Business Services\nID: 1262c350-fe0f-40ec-aeff-41c95b4a45af\nEmail: cad@diisr.govt\nType: Unknown\nLast Updated: Sat Jul 04 2026 19:03:42 GMT+0100 (英国夏令时间)\nStatus: ACTIVE"
    },
    {
      "type": "text",
      "text": "Contact: Port & Philip Freight\nID: 847933f0-7c35-4e5b-b884-5f9df64c8e4b\nEmail: mary.port@porta.com\nType: Unknown\nLast Updated: Sat Jul 04 2026 19:03:42 GMT+0100 (英国夏令时间)\nStatus: ACTIVE"
    },
    {
      "type": "text",
      "text": "Contact: Young Bros Transport\nID: 94a82e91-53da-4f87-a417-63d6a1607ced\nEmail: rog@ybt.co\nType: Unknown\nLast Updated: Sat Jul 04 2026 19:03:42 GMT+0100 (英国夏令时间)\nStatus: ACTIVE"
    },
    {
      "type": "text",
      "text": "Contact: Boom FM\nID: 9ce626d2-14ea-463c-9fff-6785ab5f9bfb\nNo email\nType: Unknown\nLast Updated: Sat Jul 04 2026 19:03:42 GMT+0100 (英国夏令时间)\nStatus: ACTIVE"
    },
    {
      "type": "text",
      "text": "Contact: Ridgeway University\nID: a871a956-05b5-4e2a-9419-7aeb478ca647\nNo email\nType: Unknown\nLast Updated: Sat Jul 04 2026 19:03:42 GMT+0100 (英国夏令时间)\nStatus: ACTIVE"
    },
    {
      "type": "text",
      "text": "Contact: City Agency\nID: 2dd82f49-e818-4dd0-955b-b637ccaa5597\nNo email\nType: Unknown\nLast Updated: Sat Jul 04 2026 19:03:42 GMT+0100 (英国夏令时间)\nStatus: ACTIVE"
    },
    {
      "type": "text",
      "text": "Contact: Rex Media Group\nID: b2c1f980-96c9-45ff-a42b-dca141936c6c\nEmail: info@rexmedia.co\nType: Unknown\nLast Updated: Sat Jul 04 2026 19:03:42 GMT+0100 (英国夏令时间)\nStatus: ACTIVE"
    },
    {
      "type": "text",
      "text": "Contact: Marine Systems\nID: 94cb6d7b-5291-49f3-a0bc-fc0c01e68575\nNo email\nType: Unknown\nLast Updated: Sat Jul 04 2026 19:03:42 GMT+0100 (英国夏令时间)\nStatus: ACTIVE"
    },
    {
      "type": "text",
      "text": "Contact: Maddox Publishing Group\nID: afd4093b-c655-4847-8ee2-10a4f2c3eae3\nNo email\nType: Unknown\nDefault Currency: GBP\nLast Updated: Sat Jul 04 2026 21:36:48 GMT+0100 (英国夏令时间)\nStatus: ACTIVE"
    },
    {
      "type": "text",
      "text": "Contact: Mobil\nID: c3c66d43-72d2-490d-b231-96bd5c3355f9\nNo email\nType: Unknown\nDefault Currency: GBP\nLast Updated: Sat Jul 04 2026 22:13:40 GMT+0100 (英国夏令时间)\nStatus: ACTIVE"
    }
  ]
}